monitorio/__init__.py
monitorio/builder.py
monitorio/cli.py
monitorio/logging_utils.py
monitorio/monitorio.css
monitorio/plugins.py
monitorio/server.py
monitorio/sites/__init__.py
monitorio/sites/ci_monitor.py
monitorio/sites/private_infra.py
monitorio/static/__init__.py
monitorio/templates/__init__.py
monitorio-0.0.6.dist-info/METADATA
monitorio-0.0.6.dist-info/WHEEL
monitorio-0.0.6.dist-info/entry_points.txt
monitorio-0.0.6.dist-info/RECORD
