Metadata-Version: 2.1
Name: monitorio
Version: 0.0.6
Summary: Monitor I/O
Home-page: https://projects.om-office.de/frans/monitorio.git
Author: Frans Fürst
Author-email: frans.fuerst@protonmail.com
Requires-Python: >=3.10,<4.0.0
Classifier: Programming Language :: Python :: 3
Classifier: Programming Language :: Python :: 3.10
Classifier: Programming Language :: Python :: 3.11
Requires-Dist: asyncinotify (>=4.0.1,<5.0.0)
Requires-Dist: asyncssh (>=2.13.2,<3.0.0)
Requires-Dist: bcrypt (>=4.0.1,<5.0.0)
Requires-Dist: chime (>=0.7.0,<0.8.0)
Requires-Dist: quart (>=0.18.4,<0.19.0)
Requires-Dist: textual (>=0.32.0,<0.33.0)
Project-URL: Repository, https://projects.om-office.de/frans/monitorio.git
